week 13/ex/alu_decoder.v
module alu_decoder(
    input [1:0] ALUOp,
    input [5:0] funct,
    output reg [2:0] ALUControl
);

always @(ALUOp, funct)
begin
    case (ALUOp)
        2'b10:
        begin
            case (funct)
                6'h20:
						 begin
							  ALUControl <= 3'b010;
						 end
                6'h22:
						 begin
							  ALUControl <= 3'b110;
						 end
                6'h24:
						 begin
							  ALUControl <= 3'b000;
						 end
                6'h25:
						 begin
							  ALUControl <= 3'b001;
						 end
                6'h2A:
						 begin
							  ALUControl <= 3'b111;
						 end
            endcase
        end
		  2'b01:
        begin
            ALUControl <= 3'b110;
        end
		  2'b00:
        begin
            ALUControl <= 3'b010;
        end
        

    endcase
end

endmodule

week 13/ex/main_decoder.v
module main_decoder(
    input [5:0] opcode,
    output MemToReg, MemWrite, Branch, ALUSrc, RegDst, RegWrite, 
    output [1:0] ALUOp
);

reg MemToReg_1;
reg MemWrite_1; 
reg Branch_1;
reg ALUSrc_1;
reg RegDst_1; 
reg RegWrite_1;
reg [1:0] ALUOp_1;

assign ALUOp = ALUOp_1;
assign MemToReg = MemToReg_1;
assign MemWrite = MemWrite_1;
assign Branch = Branch_1;
assign ALUSrc = ALUSrc_1;
assign RegDst = RegDst_1;
assign RegWrite = RegWrite_1;

always @*
begin
    case (opcode)
        6'h04:
        begin
            RegWrite_1 = 1'b0;
            ALUSrc_1 = 1'b0;
            Branch_1 = 1'b1;
            MemWrite_1 = 1'b0;
            ALUOp_1 = 2'b01;
        end
		  6'h2B:
        begin
            RegWrite_1 = 1'b0;
            ALUSrc_1 = 1'b1;
            Branch_1 = 1'b0;
            MemWrite_1 = 1'b1;
            ALUOp_1 = 2'b00;
        end
        6'h23:   
        begin
            RegWrite_1 = 1'b1;
            RegDst_1 = 1'b0;
            ALUSrc_1 = 1'b1;
            Branch_1 = 1'b0;
            MemWrite_1 = 1'b0;
            MemToReg_1 = 1'b1;
            ALUOp_1 = 2'b00;
        end
        6'h00:  
        begin   
            RegWrite_1 = 1'b1;
            RegDst_1 = 1'b1;
            ALUSrc_1 = 1'b0;
            Branch_1 = 1'b0;
            MemWrite_1 = 1'b0;
            MemToReg_1 = 1'b0;
            ALUOp_1 = 2'b10;
        end
        
    endcase
end

endmodule

week 13/ex/control_unit.v
module ex(
	input [5:0] opcode, funct,
	output MemtoReg, MemWrite, Branch, ALUSrc, RegDst, RegWrite,
 	output [2:0] ALUControl
);

	wire [1:0] ALUOp;

	main_decoder md(opcode, MemtoReg, MemWrite, Branch, ALUSrc, RegDst, RegWrite, ALUOp);
	alu_decoder ad(ALUOp, funct, ALUControl);

endmodule

week 13/ex/testbench.v
module testbench;

// input and output test signals
reg [5:0] opcode, funct;
wire MemtoReg, MemWrite, Branch, ALUSrc, RegDst, RegWrite;
wire [2:0] ALUControl;

ex cu(opcode, funct, MemtoReg, MemWrite, Branch, ALUSrc, RegDst, RegWrite, ALUControl);

initial
begin
opcode = 6'h00;
funct = 6'h20;
#5;
funct = 6'h22;
#5;
funct = 6'h24;
#5;
funct = 6'h25;
#5;
funct = 6'h2A;
#5;
opcode = 6'h23;
#5;
opcode = 6'h2B;
#5;
opcode = 6'h04;
end

initial
$monitor("opcode = 0x%h RegWrite = %b RegDst = %b ALUSrc = %b Branch = %b MemWrite = %b MemtoReg = %b funct = 0x%h ALUControl = %b", opcode, RegWrite, RegDst, ALUSrc, Branch, MemWrite, MemtoReg, funct, ALUControl);

initial
$dumpvars;

endmodule

week 13/ex/simulation/modelsim/dump.vcd
$date
	Thu Nov 26 17:23:18 2020
$end
$version
	ModelSim Version 10.5b
$end
$timescale
	1ps
$end

$scope module testbench $end
$var reg 6 ! opcode [5:0] $end
$var reg 6 " funct [5:0] $end
$var wire 1 # MemtoReg $end
$var wire 1 $ MemWrite $end
$var wire 1 % Branch $end
$var wire 1 & ALUSrc $end
$var wire 1 ' RegDst $end
$var wire 1 ( RegWrite $end
$var wire 1 ) ALUControl [2] $end
$var wire 1 * ALUControl [1] $end
$var wire 1 + ALUControl [0] $end

$scope module cu $end
$var wire 1 , opcode [5] $end
$var wire 1 - opcode [4] $end
$var wire 1 . opcode [3] $end
$var wire 1 / opcode [2] $end
$var wire 1 0 opcode [1] $end
$var wire 1 1 opcode [0] $end
$var wire 1 2 funct [5] $end
$var wire 1 3 funct [4] $end
$var wire 1 4 funct [3] $end
$var wire 1 5 funct [2] $end
$var wire 1 6 funct [1] $end
$var wire 1 7 funct [0] $end
$var wire 1 # MemtoReg $end
$var wire 1 $ MemWrite $end
$var wire 1 % Branch $end
$var wire 1 & ALUSrc $end
$var wire 1 ' RegDst $end
$var wire 1 ( RegWrite $end
$var wire 1 ) ALUControl [2] $end
$var wire 1 * ALUControl [1] $end
$var wire 1 + ALUControl [0] $end
$var wire 1 8 ALUOp [1] $end
$var wire 1 9 ALUOp [0] $end

$scope module md $end
$var wire 1 , opcode [5] $end
$var wire 1 - opcode [4] $end
$var wire 1 . opcode [3] $end
$var wire 1 / opcode [2] $end
$var wire 1 0 opcode [1] $end
$var wire 1 1 opcode [0] $end
$var wire 1 # MemToReg $end
$var wire 1 $ MemWrite $end
$var wire 1 % Branch $end
$var wire 1 & ALUSrc $end
$var wire 1 ' RegDst $end
$var wire 1 ( RegWrite $end
$var wire 1 8 ALUOp [1] $end
$var wire 1 9 ALUOp [0] $end
$var reg 1 : MemToReg_1 $end
$var reg 1 ; MemWrite_1 $end
$var reg 1 < Branch_1 $end
$var reg 1 = ALUSrc_1 $end
$var reg 1 > RegDst_1 $end
$var reg 1 ? RegWrite_1 $end
$var reg 2 @ ALUOp_1 [1:0] $end
$upscope $end

$scope module ad $end
$var wire 1 8 ALUOp [1] $end
$var wire 1 9 ALUOp [0] $end
$var wire 1 2 funct [5] $end
$var wire 1 3 funct [4] $end
$var wire 1 4 funct [3] $end
$var wire 1 5 funct [2] $end
$var wire 1 6 funct [1] $end
$var wire 1 7 funct [0] $end
$var reg 3 A ALUControl [2:0] $end
$upscope $end
$upscope $end
$upscope $end
$enddefinitions $end
#0
$dumpvars
b0 !
b100000 "
0:
0;
0<
0=
1>
1?
b10 @
b10 A
0#
0$
0%
0&
1'
1(
0+
1*
0)
09
18
07
06
05
04
03
12
01
00
0/
0.
0-
0,
$end
#5
b100010 "
16
b110 A
1)
#10
b100100 "
06
15
b0 A
0*
0)
#15
b100101 "
17
b1 A
1+
#20
b101010 "
07
16
05
14
b111 A
1*
1)
#25
b100011 !
11
10
1,
0>
1=
1:
b0 @
0'
1&
1#
08
b10 A
0+
0)
#30
b101011 !
1.
0?
1;
0(
1$
#35
b100 !
01
00
1/
0.
0,
0=
1<
0;
b1 @
0&
1%
0$
19
b110 A
1)
